xaal/__init__.py
xaal/bugone/__init__.py
xaal/bugone/__main__.py
xaal/bugone/gw.py
xaal/bugone/nodes/__init__.py
xaal/bugone/nodes/default.py
xaal/bugone/nodes/minishield1.py
xaal/bugone/nodes/temp1.py
xaal_bugone-0.1.4.dist-info/METADATA
xaal_bugone-0.1.4.dist-info/WHEEL
xaal_bugone-0.1.4.dist-info/top_level.txt
xaal_bugone-0.1.4.dist-info/RECORD
