Metadata-Version: 2.4
Name: xaal.bugone
Version: 0.1.4
Summary: xAAL devices for bugNet wireless sensors
Author-email: Jerome Kerdreux <Jerome.Kerdreux@imt-atlantique.fr>
License-Expression: GPL-3.0-or-later
Project-URL: Homepage, https://recherche.imt-atlantique.fr/xaal/
Project-URL: Documentation, https://gitlab.imt-atlantique.fr/xaal/code/python/-/blob/main/devices/protocols/bugOne/README.rst
Project-URL: Source, https://gitlab.imt-atlantique.fr/xaal/code/python/-/tree/main/devices/protocols/bugOne
Keywords: xaal,bugone,RFM12,Wireless,Sensor
Classifier: Programming Language :: Python
Classifier: Topic :: Software Development :: Libraries :: Python Modules
Requires-Dist: xaal.lib
Requires-Dist: bugone
Requires-Dist: gevent
